<?xml version="1.0" encoding="UTF-8"?>
<doublecmd>
  <History>
    <Navigation>
      <Item>/home/ruben/.config/lnk/</Item>
      <Item>/home/ruben/.config/</Item>
      <Item>/home/ruben/.config/fish/</Item>
      <Item>/home/ruben/.config/lnk/casa.lnk/</Item>
      <Item>/home/ruben/.config/lnk/casa.lnk/.config/</Item>
      <Item>/home/ruben/.config/gtk-3.0/</Item>
      <Item>/home/ruben/</Item>
      <Item>/home/ruben/.config/lnk/casa.lnk/.config/gtk-3.0/</Item>
      <Item>/home/ruben/.config/niri/</Item>
      <Item>/home/ruben/.config/lnk/ofi.lnk/</Item>
      <Item>/media/insync/DATA/arqueon-conf/</Item>
      <Item>/media/insync/DATA/arqueon-conf/_various/</Item>
      <Item>/media/insync/DATA/arqueon-conf/home/</Item>
      <Item>/home/ruben/.config/niri/waybar/</Item>
      <Item>/media/insync/DATA/arqueon-conf/.git/</Item>
      <Item>/media/insync/DATA/arqueon-conf/.git/branches/</Item>
      <Item>/home/</Item>
      <Item>/media/insync/DATA/arqueon-conf/home/.config/</Item>
      <Item>/media/insync/DATA/arqueon-conf/home/.config/gtk-3.0/</Item>
      <Item>/home/ruben/.ssh/</Item>
      <Item>/home/ruben/.config/lnk/.config/</Item>
      <Item>/home/ruben/.config/gtk-4.0/</Item>
      <Item>/home/ruben/.config/alacritty/</Item>
      <Item>/media/insync/DATA/arqueon-conf/home/wallpaper/</Item>
      <Item>/media/insync/DATA/arqueon-conf/home/assets/</Item>
      <Item>/media/insync/DATA/</Item>
      <Item>/media/insync/</Item>
      <Item>/media/</Item>
      <Item>/</Item>
      <Item>/usr/lib/</Item>
    </Navigation>
    <CommandLine/>
    <FileMask/>
    <VolumeSize/>
    <CreateDirectories/>
    <SearchText/>
    <SearchTextPath/>
    <ReplaceText/>
    <ReplaceTextPath/>
    <RenameNameMask/>
    <RenameExtMask/>
    <SearchDirectories/>
    <SearchExcludeFiles/>
    <SearchExcludeDirectories/>
  </History>
</doublecmd>
